odoo/addons/sale_order_line_form_action/LICENSE
odoo/addons/sale_order_line_form_action/README.rst
odoo/addons/sale_order_line_form_action/__init__.py
odoo/addons/sale_order_line_form_action/__manifest__.py
odoo/addons/sale_order_line_form_action/images/screen.png
odoo/addons/sale_order_line_form_action/models/__init__.py
odoo/addons/sale_order_line_form_action/models/sale_order.py
odoo/addons/sale_order_line_form_action/readme/CONTRIBUTORS.md
odoo/addons/sale_order_line_form_action/readme/DESCRIPTION.md
odoo/addons/sale_order_line_form_action/readme/USAGE.md
odoo/addons/sale_order_line_form_action/static/description/icon.png
odoo/addons/sale_order_line_form_action/static/description/index.html
odoo/addons/sale_order_line_form_action/tests/TEST_INSTRUCTIONS.rst
odoo/addons/sale_order_line_form_action/views/sale_order.xml
odoo/addons/sale_order_line_form_action/views/sale_order_line.xml
odoo_addon_sale_order_line_form_action-18.0.1.0.0.dist-info/METADATA
odoo_addon_sale_order_line_form_action-18.0.1.0.0.dist-info/WHEEL
odoo_addon_sale_order_line_form_action-18.0.1.0.0.dist-info/top_level.txt
odoo_addon_sale_order_line_form_action-18.0.1.0.0.dist-info/RECORD
